package_nachiketa/__init__.py
package_nachiketa-1.0.0.dist-info/Licence.txt
package_nachiketa-1.0.0.dist-info/METADATA
package_nachiketa-1.0.0.dist-info/WHEEL
package_nachiketa-1.0.0.dist-info/top_level.txt
package_nachiketa-1.0.0.dist-info/RECORD
